[
    {
        "login": "linces",
        "id": 45243,
        "node_id": "MDQ6VXNlcjQ1MjQz",
        "avatar_url": "https://avatars.githubusercontent.com/u/45243?v=4",
        "gravatar_id": "",
        "url": "https://api.github.com/users/linces",
        "html_url": "https://github.com/linces",
        "followers_url": "https://api.github.com/users/linces/followers",
        "following_url": "https://api.github.com/users/linces/following{/other_user}",
        "gists_url": "https://api.github.com/users/linces/gists{/gist_id}",
        "starred_url": "https://api.github.com/users/linces/starred{/owner}{/repo}",
        "subscriptions_url": "https://api.github.com/users/linces/subscriptions",
        "organizations_url": "https://api.github.com/users/linces/orgs",
        "repos_url": "https://api.github.com/users/linces/repos",
        "events_url": "https://api.github.com/users/linces/events{/privacy}",
        "received_events_url": "https://api.github.com/users/linces/received_events",
        "type": "User",
        "site_admin": false
    },
    {
        "login": "fivetop",
        "id": 50413,
        "node_id": "MDQ6VXNlcjUwNDEz",
        "avatar_url": "https://avatars.githubusercontent.com/u/50413?v=4",
        "gravatar_id": "",
        "url": "https://api.github.com/users/fivetop",
        "html_url": "https://github.com/fivetop",
        "followers_url": "https://api.github.com/users/fivetop/followers",
        "following_url": "https://api.github.com/users/fivetop/following{/other_user}",
        "gists_url": "https://api.github.com/users/fivetop/gists{/gist_id}",
        "starred_url": "https://api.github.com/users/fivetop/starred{/owner}{/repo}",
        "subscriptions_url": "https://api.github.com/users/fivetop/subscriptions",
        "organizations_url": "https://api.github.com/users/fivetop/orgs",
        "repos_url": "https://api.github.com/users/fivetop/repos",
        "events_url": "https://api.github.com/users/fivetop/events{/privacy}",
        "received_events_url": "https://api.github.com/users/fivetop/received_events",
        "type": "User",
        "site_admin": false
    },
    {
        "login": "qawemlilo",
        "id": 363359,
        "node_id": "MDQ6VXNlcjM2MzM1OQ==",
        "avatar_url": "https://avatars.githubusercontent.com/u/363359?v=4",
        "gravatar_id": "",
        "url": "https://api.github.com/users/qawemlilo",
        "html_url": "https://github.com/qawemlilo",
        "followers_url": "https://api.github.com/users/qawemlilo/followers",
        "following_url": "https://api.github.com/users/qawemlilo/following{/other_user}",
        "gists_url": "https://api.github.com/users/qawemlilo/gists{/gist_id}",
        "starred_url": "https://api.github.com/users/qawemlilo/starred{/owner}{/repo}",
        "subscriptions_url": "https://api.github.com/users/qawemlilo/subscriptions",
        "organizations_url": "https://api.github.com/users/qawemlilo/orgs",
        "repos_url": "https://api.github.com/users/qawemlilo/repos",
        "events_url": "https://api.github.com/users/qawemlilo/events{/privacy}",
        "received_events_url": "https://api.github.com/users/qawemlilo/received_events",
        "type": "User",
        "site_admin": false
    },
    {
        "login": "jeffersonsimaogoncalves",
        "id": 411493,
        "node_id": "MDQ6VXNlcjQxMTQ5Mw==",
        "avatar_url": "https://avatars.githubusercontent.com/u/411493?v=4",
        "gravatar_id": "",
        "url": "https://api.github.com/users/jeffersonsimaogoncalves",
        "html_url": "https://github.com/jeffersonsimaogoncalves",
        "followers_url": "https://api.github.com/users/jeffersonsimaogoncalves/followers",
        "following_url": "https://api.github.com/users/jeffersonsimaogoncalves/following{/other_user}",
        "gists_url": "https://api.github.com/users/jeffersonsimaogoncalves/gists{/gist_id}",
        "starred_url": "https://api.github.com/users/jeffersonsimaogoncalves/starred{/owner}{/repo}",
        "subscriptions_url": "https://api.github.com/users/jeffersonsimaogoncalves/subscriptions",
        "organizations_url": "https://api.github.com/users/jeffersonsimaogoncalves/orgs",
        "repos_url": "https://api.github.com/users/jeffersonsimaogoncalves/repos",
        "events_url": "https://api.github.com/users/jeffersonsimaogoncalves/events{/privacy}",
        "received_events_url": "https://api.github.com/users/jeffersonsimaogoncalves/received_events",
        "type": "User",
        "site_admin": false
    },
    {
        "login": "mrothauer",
        "id": 527787,
        "node_id": "MDQ6VXNlcjUyNzc4Nw==",
        "avatar_url": "https://avatars.githubusercontent.com/u/527787?v=4",
        "gravatar_id": "",
        "url": "https://api.github.com/users/mrothauer",
        "html_url": "https://github.com/mrothauer",
        "followers_url": "https://api.github.com/users/mrothauer/followers",
        "following_url": "https://api.github.com/users/mrothauer/following{/other_user}",
        "gists_url": "https://api.github.com/users/mrothauer/gists{/gist_id}",
        "starred_url": "https://api.github.com/users/mrothauer/starred{/owner}{/repo}",
        "subscriptions_url": "https://api.github.com/users/mrothauer/subscriptions",
        "organizations_url": "https://api.github.com/users/mrothauer/orgs",
        "repos_url": "https://api.github.com/users/mrothauer/repos",
        "events_url": "https://api.github.com/users/mrothauer/events{/privacy}",
        "received_events_url": "https://api.github.com/users/mrothauer/received_events",
        "type": "User",
        "site_admin": false
    },
    {
        "login": "R-K-H",
        "id": 1007667,
        "node_id": "MDQ6VXNlcjEwMDc2Njc=",
        "avatar_url": "https://avatars.githubusercontent.com/u/1007667?v=4",
        "gravatar_id": "",
        "url": "https://api.github.com/users/R-K-H",
        "html_url": "https://github.com/R-K-H",
        "followers_url": "https://api.github.com/users/R-K-H/followers",
        "following_url": "https://api.github.com/users/R-K-H/following{/other_user}",
        "gists_url": "https://api.github.com/users/R-K-H/gists{/gist_id}",
        "starred_url": "https://api.github.com/users/R-K-H/starred{/owner}{/repo}",
        "subscriptions_url": "https://api.github.com/users/R-K-H/subscriptions",
        "organizations_url": "https://api.github.com/users/R-K-H/orgs",
        "repos_url": "https://api.github.com/users/R-K-H/repos",
        "events_url": "https://api.github.com/users/R-K-H/events{/privacy}",
        "received_events_url": "https://api.github.com/users/R-K-H/received_events",
        "type": "User",
        "site_admin": false
    },
    {
        "login": "devpro",
        "id": 1216802,
        "node_id": "MDQ6VXNlcjEyMTY4MDI=",
        "avatar_url": "https://avatars.githubusercontent.com/u/1216802?v=4",
        "gravatar_id": "",
        "url": "https://api.github.com/users/devpro",
        "html_url": "https://github.com/devpro",
        "followers_url": "https://api.github.com/users/devpro/followers",
        "following_url": "https://api.github.com/users/devpro/following{/other_user}",
        "gists_url": "https://api.github.com/users/devpro/gists{/gist_id}",
        "starred_url": "https://api.github.com/users/devpro/starred{/owner}{/repo}",
        "subscriptions_url": "https://api.github.com/users/devpro/subscriptions",
        "organizations_url": "https://api.github.com/users/devpro/orgs",
        "repos_url": "https://api.github.com/users/devpro/repos",
        "events_url": "https://api.github.com/users/devpro/events{/privacy}",
        "received_events_url": "https://api.github.com/users/devpro/received_events",
        "type": "User",
        "site_admin": false
    },
    {
        "login": "PlumpMath",
        "id": 1218365,
        "node_id": "MDQ6VXNlcjEyMTgzNjU=",
        "avatar_url": "https://avatars.githubusercontent.com/u/1218365?v=4",
        "gravatar_id": "",
        "url": "https://api.github.com/users/PlumpMath",
        "html_url": "https://github.com/PlumpMath",
        "followers_url": "https://api.github.com/users/PlumpMath/followers",
        "following_url": "https://api.github.com/users/PlumpMath/following{/other_user}",
        "gists_url": "https://api.github.com/users/PlumpMath/gists{/gist_id}",
        "starred_url": "https://api.github.com/users/PlumpMath/starred{/owner}{/repo}",
        "subscriptions_url": "https://api.github.com/users/PlumpMath/subscriptions",
        "organizations_url": "https://api.github.com/users/PlumpMath/orgs",
        "repos_url": "https://api.github.com/users/PlumpMath/repos",
        "events_url": "https://api.github.com/users/PlumpMath/events{/privacy}",
        "received_events_url": "https://api.github.com/users/PlumpMath/received_events",
        "type": "User",
        "site_admin": false
    },
    {
        "login": "lykmapipo",
        "id": 1610857,
        "node_id": "MDQ6VXNlcjE2MTA4NTc=",
        "avatar_url": "https://avatars.githubusercontent.com/u/1610857?v=4",
        "gravatar_id": "",
        "url": "https://api.github.com/users/lykmapipo",
        "html_url": "https://github.com/lykmapipo",
        "followers_url": "https://api.github.com/users/lykmapipo/followers",
        "following_url": "https://api.github.com/users/lykmapipo/following{/other_user}",
        "gists_url": "https://api.github.com/users/lykmapipo/gists{/gist_id}",
        "starred_url": "https://api.github.com/users/lykmapipo/starred{/owner}{/repo}",
        "subscriptions_url": "https://api.github.com/users/lykmapipo/subscriptions",
        "organizations_url": "https://api.github.com/users/lykmapipo/orgs",
        "repos_url": "https://api.github.com/users/lykmapipo/repos",
        "events_url": "https://api.github.com/users/lykmapipo/events{/privacy}",
        "received_events_url": "https://api.github.com/users/lykmapipo/received_events",
        "type": "User",
        "site_admin": false
    },
    {
        "login": "trinhminhtriet",
        "id": 1650997,
        "node_id": "MDQ6VXNlcjE2NTA5OTc=",
        "avatar_url": "https://avatars.githubusercontent.com/u/1650997?v=4",
        "gravatar_id": "",
        "url": "https://api.github.com/users/trinhminhtriet",
        "html_url": "https://github.com/trinhminhtriet",
        "followers_url": "https://api.github.com/users/trinhminhtriet/followers",
        "following_url": "https://api.github.com/users/trinhminhtriet/following{/other_user}",
        "gists_url": "https://api.github.com/users/trinhminhtriet/gists{/gist_id}",
        "starred_url": "https://api.github.com/users/trinhminhtriet/starred{/owner}{/repo}",
        "subscriptions_url": "https://api.github.com/users/trinhminhtriet/subscriptions",
        "organizations_url": "https://api.github.com/users/trinhminhtriet/orgs",
        "repos_url": "https://api.github.com/users/trinhminhtriet/repos",
        "events_url": "https://api.github.com/users/trinhminhtriet/events{/privacy}",
        "received_events_url": "https://api.github.com/users/trinhminhtriet/received_events",
        "type": "User",
        "site_admin": false
    },
    {
        "login": "artkirienko",
        "id": 2473081,
        "node_id": "MDQ6VXNlcjI0NzMwODE=",
        "avatar_url": "https://avatars.githubusercontent.com/u/2473081?v=4",
        "gravatar_id": "",
        "url": "https://api.github.com/users/artkirienko",
        "html_url": "https://github.com/artkirienko",
        "followers_url": "https://api.github.com/users/artkirienko/followers",
        "following_url": "https://api.github.com/users/artkirienko/following{/other_user}",
        "gists_url": "https://api.github.com/users/artkirienko/gists{/gist_id}",
        "starred_url": "https://api.github.com/users/artkirienko/starred{/owner}{/repo}",
        "subscriptions_url": "https://api.github.com/users/artkirienko/subscriptions",
        "organizations_url": "https://api.github.com/users/artkirienko/orgs",
        "repos_url": "https://api.github.com/users/artkirienko/repos",
        "events_url": "https://api.github.com/users/artkirienko/events{/privacy}",
        "received_events_url": "https://api.github.com/users/artkirienko/received_events",
        "type": "User",
        "site_admin": false
    },
    {
        "login": "RINEARN",
        "id": 2651961,
        "node_id": "MDQ6VXNlcjI2NTE5NjE=",
        "avatar_url": "https://avatars.githubusercontent.com/u/2651961?v=4",
        "gravatar_id": "",
        "url": "https://api.github.com/users/RINEARN",
        "html_url": "https://github.com/RINEARN",
        "followers_url": "https://api.github.com/users/RINEARN/followers",
        "following_url": "https://api.github.com/users/RINEARN/following{/other_user}",
        "gists_url": "https://api.github.com/users/RINEARN/gists{/gist_id}",
        "starred_url": "https://api.github.com/users/RINEARN/starred{/owner}{/repo}",
        "subscriptions_url": "https://api.github.com/users/RINEARN/subscriptions",
        "organizations_url": "https://api.github.com/users/RINEARN/orgs",
        "repos_url": "https://api.github.com/users/RINEARN/repos",
        "events_url": "https://api.github.com/users/RINEARN/events{/privacy}",
        "received_events_url": "https://api.github.com/users/RINEARN/received_events",
        "type": "User",
        "site_admin": false
    },
    {
        "login": "dsfb",
        "id": 2995775,
        "node_id": "MDQ6VXNlcjI5OTU3NzU=",
        "avatar_url": "https://avatars.githubusercontent.com/u/2995775?v=4",
        "gravatar_id": "",
        "url": "https://api.github.com/users/dsfb",
        "html_url": "https://github.com/dsfb",
        "followers_url": "https://api.github.com/users/dsfb/followers",
        "following_url": "https://api.github.com/users/dsfb/following{/other_user}",
        "gists_url": "https://api.github.com/users/dsfb/gists{/gist_id}",
        "starred_url": "https://api.github.com/users/dsfb/starred{/owner}{/repo}",
        "subscriptions_url": "https://api.github.com/users/dsfb/subscriptions",
        "organizations_url": "https://api.github.com/users/dsfb/orgs",
        "repos_url": "https://api.github.com/users/dsfb/repos",
        "events_url": "https://api.github.com/users/dsfb/events{/privacy}",
        "received_events_url": "https://api.github.com/users/dsfb/received_events",
        "type": "User",
        "site_admin": false
    },
    {
        "login": "ab25cq",
        "id": 3233635,
        "node_id": "MDQ6VXNlcjMyMzM2MzU=",
        "avatar_url": "https://avatars.githubusercontent.com/u/3233635?v=4",
        "gravatar_id": "",
        "url": "https://api.github.com/users/ab25cq",
        "html_url": "https://github.com/ab25cq",
        "followers_url": "https://api.github.com/users/ab25cq/followers",
        "following_url": "https://api.github.com/users/ab25cq/following{/other_user}",
        "gists_url": "https://api.github.com/users/ab25cq/gists{/gist_id}",
        "starred_url": "https://api.github.com/users/ab25cq/starred{/owner}{/repo}",
        "subscriptions_url": "https://api.github.com/users/ab25cq/subscriptions",
        "organizations_url": "https://api.github.com/users/ab25cq/orgs",
        "repos_url": "https://api.github.com/users/ab25cq/repos",
        "events_url": "https://api.github.com/users/ab25cq/events{/privacy}",
        "received_events_url": "https://api.github.com/users/ab25cq/received_events",
        "type": "User",
        "site_admin": false
    },
    {
        "login": "freskoulix",
        "id": 3754652,
        "node_id": "MDQ6VXNlcjM3NTQ2NTI=",
        "avatar_url": "https://avatars.githubusercontent.com/u/3754652?v=4",
        "gravatar_id": "",
        "url": "https://api.github.com/users/freskoulix",
        "html_url": "https://github.com/freskoulix",
        "followers_url": "https://api.github.com/users/freskoulix/followers",
        "following_url": "https://api.github.com/users/freskoulix/following{/other_user}",
        "gists_url": "https://api.github.com/users/freskoulix/gists{/gist_id}",
        "starred_url": "https://api.github.com/users/freskoulix/starred{/owner}{/repo}",
        "subscriptions_url": "https://api.github.com/users/freskoulix/subscriptions",
        "organizations_url": "https://api.github.com/users/freskoulix/orgs",
        "repos_url": "https://api.github.com/users/freskoulix/repos",
        "events_url": "https://api.github.com/users/freskoulix/events{/privacy}",
        "received_events_url": "https://api.github.com/users/freskoulix/received_events",
        "type": "User",
        "site_admin": false
    },
    {
        "login": "Soldy",
        "id": 4786022,
        "node_id": "MDQ6VXNlcjQ3ODYwMjI=",
        "avatar_url": "https://avatars.githubusercontent.com/u/4786022?v=4",
        "gravatar_id": "",
        "url": "https://api.github.com/users/Soldy",
        "html_url": "https://github.com/Soldy",
        "followers_url": "https://api.github.com/users/Soldy/followers",
        "following_url": "https://api.github.com/users/Soldy/following{/other_user}",
        "gists_url": "https://api.github.com/users/Soldy/gists{/gist_id}",
        "starred_url": "https://api.github.com/users/Soldy/starred{/owner}{/repo}",
        "subscriptions_url": "https://api.github.com/users/Soldy/subscriptions",
        "organizations_url": "https://api.github.com/users/Soldy/orgs",
        "repos_url": "https://api.github.com/users/Soldy/repos",
        "events_url": "https://api.github.com/users/Soldy/events{/privacy}",
        "received_events_url": "https://api.github.com/users/Soldy/received_events",
        "type": "User",
        "site_admin": false
    },
    {
        "login": "ilkerhalil",
        "id": 5356826,
        "node_id": "MDQ6VXNlcjUzNTY4MjY=",
        "avatar_url": "https://avatars.githubusercontent.com/u/5356826?v=4",
        "gravatar_id": "",
        "url": "https://api.github.com/users/ilkerhalil",
        "html_url": "https://github.com/ilkerhalil",
        "followers_url": "https://api.github.com/users/ilkerhalil/followers",
        "following_url": "https://api.github.com/users/ilkerhalil/following{/other_user}",
        "gists_url": "https://api.github.com/users/ilkerhalil/gists{/gist_id}",
        "starred_url": "https://api.github.com/users/ilkerhalil/starred{/owner}{/repo}",
        "subscriptions_url": "https://api.github.com/users/ilkerhalil/subscriptions",
        "organizations_url": "https://api.github.com/users/ilkerhalil/orgs",
        "repos_url": "https://api.github.com/users/ilkerhalil/repos",
        "events_url": "https://api.github.com/users/ilkerhalil/events{/privacy}",
        "received_events_url": "https://api.github.com/users/ilkerhalil/received_events",
        "type": "User",
        "site_admin": false
    },
    {
        "login": "mkipnis",
        "id": 5619863,
        "node_id": "MDQ6VXNlcjU2MTk4NjM=",
        "avatar_url": "https://avatars.githubusercontent.com/u/5619863?v=4",
        "gravatar_id": "",
        "url": "https://api.github.com/users/mkipnis",
        "html_url": "https://github.com/mkipnis",
        "followers_url": "https://api.github.com/users/mkipnis/followers",
        "following_url": "https://api.github.com/users/mkipnis/following{/other_user}",
        "gists_url": "https://api.github.com/users/mkipnis/gists{/gist_id}",
        "starred_url": "https://api.github.com/users/mkipnis/starred{/owner}{/repo}",
        "subscriptions_url": "https://api.github.com/users/mkipnis/subscriptions",
        "organizations_url": "https://api.github.com/users/mkipnis/orgs",
        "repos_url": "https://api.github.com/users/mkipnis/repos",
        "events_url": "https://api.github.com/users/mkipnis/events{/privacy}",
        "received_events_url": "https://api.github.com/users/mkipnis/received_events",
        "type": "User",
        "site_admin": false
    },
    {
        "login": "ravenmk3",
        "id": 5772169,
        "node_id": "MDQ6VXNlcjU3NzIxNjk=",
        "avatar_url": "https://avatars.githubusercontent.com/u/5772169?v=4",
        "gravatar_id": "",
        "url": "https://api.github.com/users/ravenmk3",
        "html_url": "https://github.com/ravenmk3",
        "followers_url": "https://api.github.com/users/ravenmk3/followers",
        "following_url": "https://api.github.com/users/ravenmk3/following{/other_user}",
        "gists_url": "https://api.github.com/users/ravenmk3/gists{/gist_id}",
        "starred_url": "https://api.github.com/users/ravenmk3/starred{/owner}{/repo}",
        "subscriptions_url": "https://api.github.com/users/ravenmk3/subscriptions",
        "organizations_url": "https://api.github.com/users/ravenmk3/orgs",
        "repos_url": "https://api.github.com/users/ravenmk3/repos",
        "events_url": "https://api.github.com/users/ravenmk3/events{/privacy}",
        "received_events_url": "https://api.github.com/users/ravenmk3/received_events",
        "type": "User",
        "site_admin": false
    },
    {
        "login": "Hamza5",
        "id": 7011111,
        "node_id": "MDQ6VXNlcjcwMTExMTE=",
        "avatar_url": "https://avatars.githubusercontent.com/u/7011111?v=4",
        "gravatar_id": "",
        "url": "https://api.github.com/users/Hamza5",
        "html_url": "https://github.com/Hamza5",
        "followers_url": "https://api.github.com/users/Hamza5/followers",
        "following_url": "https://api.github.com/users/Hamza5/following{/other_user}",
        "gists_url": "https://api.github.com/users/Hamza5/gists{/gist_id}",
        "starred_url": "https://api.github.com/users/Hamza5/starred{/owner}{/repo}",
        "subscriptions_url": "https://api.github.com/users/Hamza5/subscriptions",
        "organizations_url": "https://api.github.com/users/Hamza5/orgs",
        "repos_url": "https://api.github.com/users/Hamza5/repos",
        "events_url": "https://api.github.com/users/Hamza5/events{/privacy}",
        "received_events_url": "https://api.github.com/users/Hamza5/received_events",
        "type": "User",
        "site_admin": false
    },
    {
        "login": "yzld2002",
        "id": 7520479,
        "node_id": "MDQ6VXNlcjc1MjA0Nzk=",
        "avatar_url": "https://avatars.githubusercontent.com/u/7520479?v=4",
        "gravatar_id": "",
        "url": "https://api.github.com/users/yzld2002",
        "html_url": "https://github.com/yzld2002",
        "followers_url": "https://api.github.com/users/yzld2002/followers",
        "following_url": "https://api.github.com/users/yzld2002/following{/other_user}",
        "gists_url": "https://api.github.com/users/yzld2002/gists{/gist_id}",
        "starred_url": "https://api.github.com/users/yzld2002/starred{/owner}{/repo}",
        "subscriptions_url": "https://api.github.com/users/yzld2002/subscriptions",
        "organizations_url": "https://api.github.com/users/yzld2002/orgs",
        "repos_url": "https://api.github.com/users/yzld2002/repos",
        "events_url": "https://api.github.com/users/yzld2002/events{/privacy}",
        "received_events_url": "https://api.github.com/users/yzld2002/received_events",
        "type": "User",
        "site_admin": false
    },
    {
        "login": "mi5t4n",
        "id": 8264719,
        "node_id": "MDQ6VXNlcjgyNjQ3MTk=",
        "avatar_url": "https://avatars.githubusercontent.com/u/8264719?v=4",
        "gravatar_id": "",
        "url": "https://api.github.com/users/mi5t4n",
        "html_url": "https://github.com/mi5t4n",
        "followers_url": "https://api.github.com/users/mi5t4n/followers",
        "following_url": "https://api.github.com/users/mi5t4n/following{/other_user}",
        "gists_url": "https://api.github.com/users/mi5t4n/gists{/gist_id}",
        "starred_url": "https://api.github.com/users/mi5t4n/starred{/owner}{/repo}",
        "subscriptions_url": "https://api.github.com/users/mi5t4n/subscriptions",
        "organizations_url": "https://api.github.com/users/mi5t4n/orgs",
        "repos_url": "https://api.github.com/users/mi5t4n/repos",
        "events_url": "https://api.github.com/users/mi5t4n/events{/privacy}",
        "received_events_url": "https://api.github.com/users/mi5t4n/received_events",
        "type": "User",
        "site_admin": false
    },
    {
        "login": "peter279k",
        "id": 9021747,
        "node_id": "MDQ6VXNlcjkwMjE3NDc=",
        "avatar_url": "https://avatars.githubusercontent.com/u/9021747?v=4",
        "gravatar_id": "",
        "url": "https://api.github.com/users/peter279k",
        "html_url": "https://github.com/peter279k",
        "followers_url": "https://api.github.com/users/peter279k/followers",
        "following_url": "https://api.github.com/users/peter279k/following{/other_user}",
        "gists_url": "https://api.github.com/users/peter279k/gists{/gist_id}",
        "starred_url": "https://api.github.com/users/peter279k/starred{/owner}{/repo}",
        "subscriptions_url": "https://api.github.com/users/peter279k/subscriptions",
        "organizations_url": "https://api.github.com/users/peter279k/orgs",
        "repos_url": "https://api.github.com/users/peter279k/repos",
        "events_url": "https://api.github.com/users/peter279k/events{/privacy}",
        "received_events_url": "https://api.github.com/users/peter279k/received_events",
        "type": "User",
        "site_admin": false
    },
    {
        "login": "kevin-06-huang",
        "id": 10319695,
        "node_id": "MDQ6VXNlcjEwMzE5Njk1",
        "avatar_url": "https://avatars.githubusercontent.com/u/10319695?v=4",
        "gravatar_id": "",
        "url": "https://api.github.com/users/kevin-06-huang",
        "html_url": "https://github.com/kevin-06-huang",
        "followers_url": "https://api.github.com/users/kevin-06-huang/followers",
        "following_url": "https://api.github.com/users/kevin-06-huang/following{/other_user}",
        "gists_url": "https://api.github.com/users/kevin-06-huang/gists{/gist_id}",
        "starred_url": "https://api.github.com/users/kevin-06-huang/starred{/owner}{/repo}",
        "subscriptions_url": "https://api.github.com/users/kevin-06-huang/subscriptions",
        "organizations_url": "https://api.github.com/users/kevin-06-huang/orgs",
        "repos_url": "https://api.github.com/users/kevin-06-huang/repos",
        "events_url": "https://api.github.com/users/kevin-06-huang/events{/privacy}",
        "received_events_url": "https://api.github.com/users/kevin-06-huang/received_events",
        "type": "User",
        "site_admin": false
    },
    {
        "login": "chrdek",
        "id": 10632099,
        "node_id": "MDQ6VXNlcjEwNjMyMDk5",
        "avatar_url": "https://avatars.githubusercontent.com/u/10632099?v=4",
        "gravatar_id": "",
        "url": "https://api.github.com/users/chrdek",
        "html_url": "https://github.com/chrdek",
        "followers_url": "https://api.github.com/users/chrdek/followers",
        "following_url": "https://api.github.com/users/chrdek/following{/other_user}",
        "gists_url": "https://api.github.com/users/chrdek/gists{/gist_id}",
        "starred_url": "https://api.github.com/users/chrdek/starred{/owner}{/repo}",
        "subscriptions_url": "https://api.github.com/users/chrdek/subscriptions",
        "organizations_url": "https://api.github.com/users/chrdek/orgs",
        "repos_url": "https://api.github.com/users/chrdek/repos",
        "events_url": "https://api.github.com/users/chrdek/events{/privacy}",
        "received_events_url": "https://api.github.com/users/chrdek/received_events",
        "type": "User",
        "site_admin": false
    },
    {
        "login": "charlesfranciscodev",
        "id": 12102640,
        "node_id": "MDQ6VXNlcjEyMTAyNjQw",
        "avatar_url": "https://avatars.githubusercontent.com/u/12102640?v=4",
        "gravatar_id": "",
        "url": "https://api.github.com/users/charlesfranciscodev",
        "html_url": "https://github.com/charlesfranciscodev",
        "followers_url": "https://api.github.com/users/charlesfranciscodev/followers",
        "following_url": "https://api.github.com/users/charlesfranciscodev/following{/other_user}",
        "gists_url": "https://api.github.com/users/charlesfranciscodev/gists{/gist_id}",
        "starred_url": "https://api.github.com/users/charlesfranciscodev/starred{/owner}{/repo}",
        "subscriptions_url": "https://api.github.com/users/charlesfranciscodev/subscriptions",
        "organizations_url": "https://api.github.com/users/charlesfranciscodev/orgs",
        "repos_url": "https://api.github.com/users/charlesfranciscodev/repos",
        "events_url": "https://api.github.com/users/charlesfranciscodev/events{/privacy}",
        "received_events_url": "https://api.github.com/users/charlesfranciscodev/received_events",
        "type": "User",
        "site_admin": false
    },
    {
        "login": "jfferson",
        "id": 12142680,
        "node_id": "MDQ6VXNlcjEyMTQyNjgw",
        "avatar_url": "https://avatars.githubusercontent.com/u/12142680?v=4",
        "gravatar_id": "",
        "url": "https://api.github.com/users/jfferson",
        "html_url": "https://github.com/jfferson",
        "followers_url": "https://api.github.com/users/jfferson/followers",
        "following_url": "https://api.github.com/users/jfferson/following{/other_user}",
        "gists_url": "https://api.github.com/users/jfferson/gists{/gist_id}",
        "starred_url": "https://api.github.com/users/jfferson/starred{/owner}{/repo}",
        "subscriptions_url": "https://api.github.com/users/jfferson/subscriptions",
        "organizations_url": "https://api.github.com/users/jfferson/orgs",
        "repos_url": "https://api.github.com/users/jfferson/repos",
        "events_url": "https://api.github.com/users/jfferson/events{/privacy}",
        "received_events_url": "https://api.github.com/users/jfferson/received_events",
        "type": "User",
        "site_admin": false
    },
    {
        "login": "yozzd",
        "id": 12942457,
        "node_id": "MDQ6VXNlcjEyOTQyNDU3",
        "avatar_url": "https://avatars.githubusercontent.com/u/12942457?v=4",
        "gravatar_id": "",
        "url": "https://api.github.com/users/yozzd",
        "html_url": "https://github.com/yozzd",
        "followers_url": "https://api.github.com/users/yozzd/followers",
        "following_url": "https://api.github.com/users/yozzd/following{/other_user}",
        "gists_url": "https://api.github.com/users/yozzd/gists{/gist_id}",
        "starred_url": "https://api.github.com/users/yozzd/starred{/owner}{/repo}",
        "subscriptions_url": "https://api.github.com/users/yozzd/subscriptions",
        "organizations_url": "https://api.github.com/users/yozzd/orgs",
        "repos_url": "https://api.github.com/users/yozzd/repos",
        "events_url": "https://api.github.com/users/yozzd/events{/privacy}",
        "received_events_url": "https://api.github.com/users/yozzd/received_events",
        "type": "User",
        "site_admin": false
    },
    {
        "login": "CelaDaniel",
        "id": 13622306,
        "node_id": "MDQ6VXNlcjEzNjIyMzA2",
        "avatar_url": "https://avatars.githubusercontent.com/u/13622306?v=4",
        "gravatar_id": "",
        "url": "https://api.github.com/users/CelaDaniel",
        "html_url": "https://github.com/CelaDaniel",
        "followers_url": "https://api.github.com/users/CelaDaniel/followers",
        "following_url": "https://api.github.com/users/CelaDaniel/following{/other_user}",
        "gists_url": "https://api.github.com/users/CelaDaniel/gists{/gist_id}",
        "starred_url": "https://api.github.com/users/CelaDaniel/starred{/owner}{/repo}",
        "subscriptions_url": "https://api.github.com/users/CelaDaniel/subscriptions",
        "organizations_url": "https://api.github.com/users/CelaDaniel/orgs",
        "repos_url": "https://api.github.com/users/CelaDaniel/repos",
        "events_url": "https://api.github.com/users/CelaDaniel/events{/privacy}",
        "received_events_url": "https://api.github.com/users/CelaDaniel/received_events",
        "type": "User",
        "site_admin": false
    },
    {
        "login": "IDouble",
        "id": 18186995,
        "node_id": "MDQ6VXNlcjE4MTg2OTk1",
        "avatar_url": "https://avatars.githubusercontent.com/u/18186995?v=4",
        "gravatar_id": "",
        "url": "https://api.github.com/users/IDouble",
        "html_url": "https://github.com/IDouble",
        "followers_url": "https://api.github.com/users/IDouble/followers",
        "following_url": "https://api.github.com/users/IDouble/following{/other_user}",
        "gists_url": "https://api.github.com/users/IDouble/gists{/gist_id}",
        "starred_url": "https://api.github.com/users/IDouble/starred{/owner}{/repo}",
        "subscriptions_url": "https://api.github.com/users/IDouble/subscriptions",
        "organizations_url": "https://api.github.com/users/IDouble/orgs",
        "repos_url": "https://api.github.com/users/IDouble/repos",
        "events_url": "https://api.github.com/users/IDouble/events{/privacy}",
        "received_events_url": "https://api.github.com/users/IDouble/received_events",
        "type": "User",
        "site_admin": false
    },
    {
        "login": "KevinTrinh1227",
        "id": 48145892,
        "node_id": "MDQ6VXNlcjQ4MTQ1ODky",
        "avatar_url": "https://avatars.githubusercontent.com/u/48145892?v=4",
        "gravatar_id": "",
        "url": "https://api.github.com/users/KevinTrinh1227",
        "html_url": "https://github.com/KevinTrinh1227",
        "followers_url": "https://api.github.com/users/KevinTrinh1227/followers",
        "following_url": "https://api.github.com/users/KevinTrinh1227/following{/other_user}",
        "gists_url": "https://api.github.com/users/KevinTrinh1227/gists{/gist_id}",
        "starred_url": "https://api.github.com/users/KevinTrinh1227/starred{/owner}{/repo}",
        "subscriptions_url": "https://api.github.com/users/KevinTrinh1227/subscriptions",
        "organizations_url": "https://api.github.com/users/KevinTrinh1227/orgs",
        "repos_url": "https://api.github.com/users/KevinTrinh1227/repos",
        "events_url": "https://api.github.com/users/KevinTrinh1227/events{/privacy}",
        "received_events_url": "https://api.github.com/users/KevinTrinh1227/received_events",
        "type": "User",
        "site_admin": false
    },
    {
        "login": "JohnMwendwa",
        "id": 72663882,
        "node_id": "MDQ6VXNlcjcyNjYzODgy",
        "avatar_url": "https://avatars.githubusercontent.com/u/72663882?v=4",
        "gravatar_id": "",
        "url": "https://api.github.com/users/JohnMwendwa",
        "html_url": "https://github.com/JohnMwendwa",
        "followers_url": "https://api.github.com/users/JohnMwendwa/followers",
        "following_url": "https://api.github.com/users/JohnMwendwa/following{/other_user}",
        "gists_url": "https://api.github.com/users/JohnMwendwa/gists{/gist_id}",
        "starred_url": "https://api.github.com/users/JohnMwendwa/starred{/owner}{/repo}",
        "subscriptions_url": "https://api.github.com/users/JohnMwendwa/subscriptions",
        "organizations_url": "https://api.github.com/users/JohnMwendwa/orgs",
        "repos_url": "https://api.github.com/users/JohnMwendwa/repos",
        "events_url": "https://api.github.com/users/JohnMwendwa/events{/privacy}",
        "received_events_url": "https://api.github.com/users/JohnMwendwa/received_events",
        "type": "User",
        "site_admin": false
    },
    {
        "login": "deromafilossali",
        "id": 87487520,
        "node_id": "MDQ6VXNlcjg3NDg3NTIw",
        "avatar_url": "https://avatars.githubusercontent.com/u/87487520?v=4",
        "gravatar_id": "",
        "url": "https://api.github.com/users/deromafilossali",
        "html_url": "https://github.com/deromafilossali",
        "followers_url": "https://api.github.com/users/deromafilossali/followers",
        "following_url": "https://api.github.com/users/deromafilossali/following{/other_user}",
        "gists_url": "https://api.github.com/users/deromafilossali/gists{/gist_id}",
        "starred_url": "https://api.github.com/users/deromafilossali/starred{/owner}{/repo}",
        "subscriptions_url": "https://api.github.com/users/deromafilossali/subscriptions",
        "organizations_url": "https://api.github.com/users/deromafilossali/orgs",
        "repos_url": "https://api.github.com/users/deromafilossali/repos",
        "events_url": "https://api.github.com/users/deromafilossali/events{/privacy}",
        "received_events_url": "https://api.github.com/users/deromafilossali/received_events",
        "type": "User",
        "site_admin": false
    },
    {
        "login": "Puneetsharma5525",
        "id": 108384826,
        "node_id": "U_kgDOBnXSOg",
        "avatar_url": "https://avatars.githubusercontent.com/u/108384826?v=4",
        "gravatar_id": "",
        "url": "https://api.github.com/users/Puneetsharma5525",
        "html_url": "https://github.com/Puneetsharma5525",
        "followers_url": "https://api.github.com/users/Puneetsharma5525/followers",
        "following_url": "https://api.github.com/users/Puneetsharma5525/following{/other_user}",
        "gists_url": "https://api.github.com/users/Puneetsharma5525/gists{/gist_id}",
        "starred_url": "https://api.github.com/users/Puneetsharma5525/starred{/owner}{/repo}",
        "subscriptions_url": "https://api.github.com/users/Puneetsharma5525/subscriptions",
        "organizations_url": "https://api.github.com/users/Puneetsharma5525/orgs",
        "repos_url": "https://api.github.com/users/Puneetsharma5525/repos",
        "events_url": "https://api.github.com/users/Puneetsharma5525/events{/privacy}",
        "received_events_url": "https://api.github.com/users/Puneetsharma5525/received_events",
        "type": "User",
        "site_admin": false
    },
    {
        "login": "sasan-farhadi",
        "id": 170890851,
        "node_id": "U_kgDOCi-WYw",
        "avatar_url": "https://avatars.githubusercontent.com/u/170890851?v=4",
        "gravatar_id": "",
        "url": "https://api.github.com/users/sasan-farhadi",
        "html_url": "https://github.com/sasan-farhadi",
        "followers_url": "https://api.github.com/users/sasan-farhadi/followers",
        "following_url": "https://api.github.com/users/sasan-farhadi/following{/other_user}",
        "gists_url": "https://api.github.com/users/sasan-farhadi/gists{/gist_id}",
        "starred_url": "https://api.github.com/users/sasan-farhadi/starred{/owner}{/repo}",
        "subscriptions_url": "https://api.github.com/users/sasan-farhadi/subscriptions",
        "organizations_url": "https://api.github.com/users/sasan-farhadi/orgs",
        "repos_url": "https://api.github.com/users/sasan-farhadi/repos",
        "events_url": "https://api.github.com/users/sasan-farhadi/events{/privacy}",
        "received_events_url": "https://api.github.com/users/sasan-farhadi/received_events",
        "type": "User",
        "site_admin": false
    },
    {
        "login": "mbahomaid",
        "id": 178747862,
        "node_id": "U_kgDOCqd51g",
        "avatar_url": "https://avatars.githubusercontent.com/u/178747862?v=4",
        "gravatar_id": "",
        "url": "https://api.github.com/users/mbahomaid",
        "html_url": "https://github.com/mbahomaid",
        "followers_url": "https://api.github.com/users/mbahomaid/followers",
        "following_url": "https://api.github.com/users/mbahomaid/following{/other_user}",
        "gists_url": "https://api.github.com/users/mbahomaid/gists{/gist_id}",
        "starred_url": "https://api.github.com/users/mbahomaid/starred{/owner}{/repo}",
        "subscriptions_url": "https://api.github.com/users/mbahomaid/subscriptions",
        "organizations_url": "https://api.github.com/users/mbahomaid/orgs",
        "repos_url": "https://api.github.com/users/mbahomaid/repos",
        "events_url": "https://api.github.com/users/mbahomaid/events{/privacy}",
        "received_events_url": "https://api.github.com/users/mbahomaid/received_events",
        "type": "User",
        "site_admin": false
    },
    {
        "login": "JaaGaaBar",
        "id": 184535326,
        "node_id": "U_kgDOCv_JHg",
        "avatar_url": "https://avatars.githubusercontent.com/u/184535326?v=4",
        "gravatar_id": "",
        "url": "https://api.github.com/users/JaaGaaBar",
        "html_url": "https://github.com/JaaGaaBar",
        "followers_url": "https://api.github.com/users/JaaGaaBar/followers",
        "following_url": "https://api.github.com/users/JaaGaaBar/following{/other_user}",
        "gists_url": "https://api.github.com/users/JaaGaaBar/gists{/gist_id}",
        "starred_url": "https://api.github.com/users/JaaGaaBar/starred{/owner}{/repo}",
        "subscriptions_url": "https://api.github.com/users/JaaGaaBar/subscriptions",
        "organizations_url": "https://api.github.com/users/JaaGaaBar/orgs",
        "repos_url": "https://api.github.com/users/JaaGaaBar/repos",
        "events_url": "https://api.github.com/users/JaaGaaBar/events{/privacy}",
        "received_events_url": "https://api.github.com/users/JaaGaaBar/received_events",
        "type": "User",
        "site_admin": false
    }
]